pg_summary/__init__.py
pg_summary/pg_summary.py
pg_summary-0.0.3.dist-info/LICENSE
pg_summary-0.0.3.dist-info/METADATA
pg_summary-0.0.3.dist-info/WHEEL
pg_summary-0.0.3.dist-info/entry_points.txt
pg_summary-0.0.3.dist-info/top_level.txt
pg_summary-0.0.3.dist-info/RECORD
