Metadata-Version: 2.1
Name: pg-summary
Version: 0.0.3
Summary: Create a summary of unique values for each column in a Postgres table or view and summarize results in an Excel workbook.
Author-email: Caleb Grant <grantcaleb22@gmail.com>
License: GNU GENERAL PUBLIC LICENSE
Project-URL: Homepage, https://pg-summary.readthedocs.io
Project-URL: Repository, https://github.com/geocoug/pg-summary
Project-URL: Issues, https://github.com/geocoug/pg-summary/issues
Keywords: PostgreSQL,DBMS,Database
Classifier: Programming Language :: Python :: 3
Classifier: Programming Language :: Python :: 3.10
Classifier: Programming Language :: Python :: 3.11
Classifier: Programming Language :: Python :: 3.12
Classifier: Operating System :: OS Independent
Classifier: Intended Audience :: Developers
Classifier: Topic :: Software Development :: Libraries :: Python Modules
Classifier: License :: OSI Approved :: GNU Lesser General Public License v3 (LGPLv3)
Requires-Python: >=3.10
License-File: LICENSE
Requires-Dist: openpyxl ==3.1.5
Requires-Dist: psycopg2-binary ==2.9.9
